jyserver/Bottle.py
jyserver/Django.py
jyserver/Flask.py
jyserver/Server.py
jyserver/__init__.py
jyserver/jscript.py
jyserver/jyserver-min.js
jyserver/jyserver.js
jyserver-0.0.5.dist-info/LICENSE
jyserver-0.0.5.dist-info/METADATA
jyserver-0.0.5.dist-info/WHEEL
jyserver-0.0.5.dist-info/top_level.txt
jyserver-0.0.5.dist-info/RECORD
