Metadata-Version: 2.1
Name: jyserver
Version: 0.0.5
Summary: Web Framework with Pythonic Javascript Syntax
Home-page: https://github.com/ftrias/jyserver
Author: Fernando Trias
Author-email: sub@trias.org
License: UNKNOWN
Platform: UNKNOWN
Classifier: Programming Language :: Python :: 3
Classifier: License :: OSI Approved :: MIT License
Classifier: Operating System :: OS Independent
Classifier: Development Status :: 4 - Beta
Classifier: Framework :: Flask
Classifier: Framework :: Django
Classifier: Framework :: Bottle
Requires-Python: >=3.6
